Promethee/Promethee.py
Promethee/__init__.py
Promethee-1.0.dist-info/METADATA
Promethee-1.0.dist-info/WHEEL
Promethee-1.0.dist-info/top_level.txt
Promethee-1.0.dist-info/RECORD
