Metadata-Version: 2.1
Name: Promethee
Version: 1.0
Summary: Promethee algorithm
Home-page: UNKNOWN
Author: Eduardo Teles, Wilson Freita, Vinícius Oliveira, Gabriel Monteiro, Josef Jaeger
License: UNKNOWN
Platform: UNKNOWN
Classifier: Programming Language :: Python :: 3
Classifier: License :: OSI Approved :: MIT License
Classifier: Operating System :: OS Independent
Requires-Python: >=3.8
Requires-Dist: pandas
